<?xml version="1.0" encoding="UTF-8"?>
<data>
	<p><ru>Перенесено из процесса #%s</ru><en>Moved from process #%s</en></p>
	<p><ru>Свойства</ru><en>Properties</en></p>
	<p><ru>Сохранить свойства</ru><en>Save properties</en></p>
	<p><ru>Пароль</ru><en>Password</en></p>
	<p><ru>Логин</ru><en>Login</en></p>
	<p><ru>Имя</ru><en>Name</en></p>
	<p><ru>Свойство</ru><en>Property</en></p>
	<p><ru>Параметр</ru><en>Parameter</en></p>
	<p><ru>Параметры (сохраняются сразу)</ru><en>Parameters (saved immediately)</en></p>
	<p><ru>Опции интерфейса</ru><en>Interface options</en></p>
	<p><ru>Да</ru><en>Yes</en></p>
	<p><ru>Нет</ru><en>No</en></p>
	<p><ru>Сохранять порядок объектов</ru><en>Preserve objects order</en></p>
	<p><ru>Последний объект сверху</ru><en>Last object on top</en></p>
	<p><ru>Открытие буфера объектов по долгому нажатию ЛКМ</ru><en>Open buffer on long left mouse press</en></p>
	<p><ru>Порядок объектов в буфере</ru><en>Order of objects in buffer</en></p>
	<p><ru>Максимальное число объектов в буфере</ru><en>Maximum objects in buffer</en></p>
	<p><ru>Текст</ru><en>Text</en></p>
	<p><ru>Показать текст конфигурации опций</ru><en>Show option's configuration text</en></p>
	<p><ru>Послать персональную новость</ru><en>Send personal news</en></p>
	<p><ru>Текст конфигурации опций</ru><en>Options configuration text</en></p>
	<p><ru>Сохранить опции</ru><en>Save options</en></p>
	<p><ru>Сохранено, для применения изменений перегрузите интерфейс нажатием Ctrl+F5</ru><en>Saved, for applying reboot the interface by Ctrl+F5</en></p>
	<p><ru>Мой профиль</ru><en>My profile</en></p>
	<p><ru>Выход</ru><en>Logout</en></p>
	<p><ru>Мои процессы</ru><en>My processes</en></p>
	<p><ru>Профиль</ru><en>Profile</en></p>
	<p><ru>Циклическая зависимость</ru><en>Cyclic dependency</en></p>
	<p><ru>Вложение</ru><en>Attach</en></p>
	<p><ru>Все</ru><en>All</en></p>
	<p><ru>** Я **</ru><en>** Me **</en></p>
	<p><ru>Выберите исполнителей</ru><en>Choose executors</en></p>
	<p><ru>Завершить</ru><en>Finish</en></p>
	<p><ru>Прервать создание</ru><en>Creation abort</en></p>
	<p><ru>Прервать создание процесса?</ru><en>Abort process creation?</en></p>
	<p><ru>Новый процесс</ru><en>New process</en></p>
	<p><ru>не указан</ru><en>undefined</en></p>
	<p><ru>Значение</ru><en>Value</en></p>	
	<p><ru>Название</ru><en>Name</en></p>
	<p><ru>К процессу привязаны</ru><en>Process links</en></p>
	<p><ru>Процесс привязан к</ru><en>The process is linked to</en></p>
	<p><ru>Связанные процессы</ru><en>Linked processes</en></p>
	<p><ru>Параметры</ru><en>Parameters</en></p>
	<p><ru>История статусов</ru><en>Status history</en></p>
	<p><ru>Пользователь</ru><en>User</en></p>
	<p><ru>Время</ru><en>Time</en></p>
	<p><ru>Закрыть</ru><en>Close</en></p>
	<p><ru>ИСПОЛНИТЕЛИ БЕЗ ГРУПП</ru><en>EXECUTORS WITHOUT GROUPS</en></p>
	<p><ru>-Я</ru><en>-I</en></p>
	<p><ru>+Я</ru><en>+I</en></p>
	<p><ru>Добавить вас в исполнители</ru><en>Add you to executors</en></p>
	<p><ru>Добавить меня в исполнители</ru><en>Add myself to executors</en></p>
	<p><ru>Удалить вас из исполнителей</ru><en>Remove you from executors</en></p>
	<p><ru>Удалить меня из исполнителей</ru><en>Remove myself from executors</en></p>
	<p><ru>исполнители</ru><en>executors</en></p>
	<p><ru>группы</ru><en>groups</en></p>
	<p><ru>Группы / исполнители</ru><en>Groups / executors</en></p>
	<p><ru>Отмена</ru><en>Cancel</en></p>
	<p><ru>Добавить в конец описания текст с именем автора и временем</ru><en>Add to the description's end with author and time</en></p>
	<p><ru>Править описание целиком (также можете кликнуть мышью по описанию)</ru><en>Edit the whole description, you may also click on it by mouse</en></p>
	<p><ru>править целиком</ru><en>edit</en></p>
	<p><ru>добавить</ru><en>add</en></p>
	<p><ru>Описание</ru><en>Description</en></p>
	<p><ru>история</ru><en>history</en></p>
	<p><ru>Данный тип процесса был удален</ru><en>This process type was removed</en></p>
	<p><ru>Удалить процесс</ru><en>Delete process</en></p>
	<p><ru>Статус</ru><en>Status</en></p>
	<p><ru>Создан</ru><en>Created</en></p>
	<p><ru>лог изменений</ru><en>change log</en></p>
	<p><ru>изменить тип</ru><en>type change</en></p>
	<p><ru>приоритет</ru><en>priority</en></p>	
	<p><ru>ПРЕДЫДУЩИЙ</ru><en>PREVIOUS</en></p>
	<p><ru>Комментарий</ru><en>Comment</en></p>
	<p><ru>в</ru><en>to</en></p>
	<p><ru>Переключить из статуса </ru><en>Change status from </en></p>
	<p><ru>Ещё</ru><en>More</en></p>
	<p><ru>Сообщения</ru><en>Messages</en></p>
	<p><ru>Объектов в буфере</ru><en>Objects in buffer</en></p>
	<p><ru>BGERP 3.0 не будет корректно работать в вашем браузере!</ru><en>BGERP 3.0 will not work correctly in this browser!</en></p>
	<p><ru>Поддерживаемые браузеры: Mozilla Firefox %s и новее, Google Chrome %s и новее, Safari %s и новее.</ru><en>Supported browsers: Mozilla Firefox %s and newer, Google Chrome %s and newer, Safari %s and newer.</en></p>
	<p><ru>Требуется повторная авторизация</ru><en>Re-authorization is required</en></p>
	<p><ru>При попытке аутентификации произошла ошибка</ru><en>Authentication error</en></p>
	<p><ru>Войти</ru><en>Login</en></p>
	<p><ru>Открытый интерфейс</ru><en>Open interface</en></p>
	<p><ru>Наименование</ru><en>Title</en></p>
	<p><ru>Вырезать</ru><en>Cut</en></p>
	<p><ru>Вставить</ru><en>Paste</en></p>
	<p><ru>Отделить</ru><en>Split</en></p>
	<p><ru>Слить</ru><en>Merge</en></p>
	<p><ru>Сообщение об ошибке</ru><en>Error message</en></p>
	<p><ru>Выделить или снять выделение всех</ru><en>Select or deselect all</en></p>
	<p><ru>Авторизация</ru><en>Authorization</en></p>
	<p><ru>Процессы</ru><en>Processes</en></p>
	<p><ru>Контрагент</ru><en>Customer</en></p>
	<p><ru>Создать</ru><en>Create</en></p>
	<p><ru>Поиск</ru><en>Search</en></p>
	<p><ru>Новости</ru><en>News</en></p>
	<p><ru>Адреса</ru><en>Addresses</en></p>
	<p><ru>Наборы прав</ru><en>Permission sets</en></p>
	<p><ru>Группы</ru><en>Groups</en></p>
	<p><ru>Пользователи</ru><en>Users</en></p>
	<p><ru>Статусы процессов</ru><en>Statuses</en></p>
	<p><ru>Типы процессов</ru><en>Process types</en></p>
	<p><ru>Очереди процессов</ru><en>Process queues</en></p>
	<p><ru>Динамический код</ru><en>Dynamic code</en></p>
	<p><ru>WEB запросы</ru><en>HTTP requests</en></p>
	<p><ru>Конфигурация</ru><en>Configuration</en></p>
	<p><ru>Статус приложения</ru><en>App status</en></p>
	<p><ru>Авторизовавшиеся пользователи</ru><en>Authenticated users</en></p>
	<p><ru>Приложение</ru><en>App</en></p>
	<p><ru>Администрирование</ru><en>Administration</en></p>
	<p><ru>Логирование</ru><en>Logging</en></p>
	<p><ru>Процесс</ru><en>Process</en></p>
	<p><ru>Искать</ru><en>Search</en></p>
	<p><ru>Для поиска введите подстороку названия и нажмите Enter</ru><en>For searching input title substring and press Enter</en></p>
	<p><ru>Для поиска введите код контрагента и нажмите Enter</ru><en>For searching input customer ID and press Enter</en></p>
	<p><ru>Поиск процесса по ID</ru><en>Search by Process ID</en></p>
	<p><ru>Для поиска введите код процесса и нажмите Enter</ru><en>For searching input process ID and press Enter</en></p>
	<p><ru>Дом/дробь</ru><en>House/frac</en></p>
	<p><ru>Квартира</ru><en>Apartment</en></p>
	<p><ru>Улица</ru><en>Street</en></p>
	<p><ru>Очистить</ru><en>Clear</en></p>
	<p><ru>Справочник</ru><en>Directory</en></p>
	<p><ru>Параметры процессов</ru><en>Process parameters</en></p>
	<p><ru>Параметры пользователей</ru><en>User parameters</en></p>
	<p><ru>Параметры контрагентов</ru><en>Customer parameters</en></p>
	<p><ru>Группы параметров контрагентов</ru><en>Customer parameters groups</en></p>
	<p><ru>Шаблоны названия контрагентов</ru><en>Parameter title patters</en></p>
	<p><ru>Параметры домов</ru><en>House parameters</en></p>
	<p><ru>Фильтр</ru><en>Filter</en></p>
	<p><ru>По наименованию, комментарию, конфигурации</ru><en>By title, comment, configuration</en></p>
	<p><ru>Интерфейс</ru><en>Interface</en></p>
	<p><ru>Выйти</ru><en>Log off</en></p>
	<p><ru>Очередь</ru><en>Queue</en></p>
	<p><ru>Период</ru><en>Period</en></p>
	<p><ru>Группа</ru><en>Group</en></p>
	<p><ru>Дата создания</ru><en>Date of creation</en></p>
	<p><ru>Дата закрытия</ru><en>Сlosing date</en></p>
	<p><ru>Любой</ru><en>Any</en></p>
	<p><ru>Тип</ru><en>Type</en></p>
	<p><ru>Открытые</ru><en>Open</en></p>
	<p><ru>Закрытые</ru><en>Closed</en></p>
	<p><ru>Закрыт</ru><en>Closed</en></p>
	<p><ru>Записей</ru><en>Records</en></p>
	<p><ru>Стр.</ru><en>Page</en></p>
	<p><ru>из</ru><en>of</en></p>
	<p><ru>Новый контрагент</ru><en>New customer</en></p>
	<p><ru>Редактирование</ru><en>Editing</en></p>
	<p><ru>Шаблон названия</ru><en>Title template</en></p>
	<p><ru>Без шаблона</ru><en>No template</en></p>
	<p><ru>Персональный шаблон</ru><en>Personal template</en></p>
	<p><ru>Персональный шаблон названия</ru><en>Personal title template</en></p>
	<p><ru>Группа параметров</ru><en>Parameter group</en></p>
	<p><ru>Группа не установлена (все параметры)</ru><en>Group not set (all parameters)</en></p>
	<p><ru>Нажатие Enter - поиск по улице</ru><en>Pressing Enter - street search</en></p>
	<p><ru>Нажатие Enter - поиск по дому</ru><en>Pressing Enter - search by house</en></p>
	<p><ru>Нажатие Enter - поиск по квартире</ru><en>Pressing Enter - search by apartment</en></p>
	<p><ru>Цвет</ru><en>Colour</en></p>
	<p><ru>Cозданные мной</ru><en>Created by me</en></p>
	<p><ru>Закрытые мной</ru><en>Closed by me</en></p>
	<p><ru>Статус изменён мной</ru><en>Status changed by me</en></p>
	<p><ru>Вывести</ru><en>Show</en></p>
	<p><ru>Вывести для</ru><en>Output for</en></p>
	<p><ru>Вывести на дату</ru><en>Output to date</en></p>
	<p><ru>Время создания</ru><en>Time of creation</en></p>
	<p><ru>Открыть</ru><en>Open</en></p>
	<p><ru>Создание новости</ru><en>News creation</en></p>
	<p><ru>Заголовок</ru><en>Title</en></p>
	<p><ru>Полный текст</ru><en>Full text</en></p>
	<p><ru>В тексте новости допустима HTML разметка.</ru><en>HTML markup is allowed in the news text.</en></p>
	<p><ru>Время на прочтение</ru><en>Time to read</en></p>
	<p><ru>Через какое количество часов новость будет помечена прочитана для адресатов независимо от фактического прочтения.</ru><en>After how many hours the news will be marked as read for the addressees, regardless of the actual reading.</en></p>
	<p><ru>Время жизни новости</ru><en>Life time news</en></p>
	<p><ru>Через какое количество суток новость будет удалена для всех адресатов.</ru><en>After how many days the news will be deleted for all recipients.</en></p>
	<p><ru>Тип новости</ru><en>News type</en></p>
	<p><ru>Обычная</ru><en>Regular</en></p>
	<p><ru>Всплывающая</ru><en>Popup</en></p>
	<p><ru>Если группы не указаны - новость получают все пользователи.</ru><en>If groups are not specified, all users receive the news.</en></p>
	<p><ru>Непрочитанные</ru><en>Unread</en></p>
	<p><ru>Прочитанные</ru><en>Read</en></p>
	<p><ru>Фильтр по тексту</ru><en>Filter by text</en></p>
	<p><ru>Создал</ru><en>Created</en></p>
	<p><ru>Удалить</ru><en>Delete</en></p>
	<p><ru>Не прочитано</ru><en>Unread</en></p>
	<p><ru>Прочитано</ru><en>Read</en></p>
	<p><ru>Пометить все новости прочитанными</ru><en>Mark all news as read</en></p>
	<p><ru>Все прочитаны</ru><en>All read</en></p>
	<p><ru>Редактор</ru><en>Editor</en></p>
	<p><ru>Помощь</ru><en>Help</en></p>
	<p><ru>Фильтры</ru><en>Filters</en></p>
	<p><ru>Сорт.</ru><en>Order</en></p>
	<p><ru>Слить в существующий</ru><en>Merge to existing</en></p>
	<p><ru>Привязки</ru><en>Links</en></p>
	<p><ru>привязать</ru><en>add link</en></p>
	<p><ru>Привязать объект из буфера</ru><en>Link object from buffer</en></p>
	<p><ru>Привязать иной объект</ru><en>Link another object</en></p>
	<p><ru>Строка поиска контрагента</ru><en>Customer search string</en></p>
	<p><ru>нет</ru><en>no</en></p>
	<p><ru>Произвольный объект</ru><en>Arbitary object</en></p>
	<p><ru>Привязать сообщение к указанному процессу?</ru><en>Link the message to the process?</en></p>
	<p><ru>Изменить процесс на</ru><en>Change process to</en></p>
	<p><ru>Независимую</ru><en>Independent</en></p>
	<p><ru>Изменить процесс сообщения на %s копию текущего процесса?</ru><en>Change process of the message to %s copy of the current process?</en></p>
	<p><ru>%s копию текущего</ru><en>%s copy of the current</en></p>
	<p><ru>Зависящую</ru><en>Dependent</en></p>
	<p><ru>Порождённую</ru><en>Made</en></p>
	<p><ru>Ссылаемую</ru><en>Linked</en></p>
	<p><ru>Привязать связанный с уже привязаным объектом</ru><en>Link a transitive linked object</en></p>
	<p><ru>Процесс создан</ru><en>Process created</en></p>
	<p><ru>Создано</ru><en>Created</en></p>
	<p><ru>Отправлено</ru><en>Sent</en></p>
	<p><ru>Обработано</ru><en>Processed</en></p>
	<p><ru>Вкл./выкл. разрывы строк</ru><en>Toggle line breaks</en></p>
	<p><ru>Удалить сообщение?</ru><en>Delete the message?</en></p>
	<p><ru>Теги</ru><en>Tags</en></p>
	<p><ru>Ответить</ru><en>Respond</en></p>
	<p><ru>Редактировать</ru><en>Edit</en></p>
	<p><ru>Другой существующий</ru><en>Another existing</en></p>
	<p><ru>Плагины</ru><en>Plugins</en></p>
	<p><ru>Фильтр по содержимому конфигурации</ru><en>Filter by configuration's content</en></p>
	<p><ru>Активный</ru><en>Active</en></p>
	<p><ru>Активные плагины</ru><en>Enabled plugins</en></p>
	<p><ru>Лицензия</ru><en>License</en></p>
	<p><ru>Иниациализировать плагины</ru><en>Initialize plugins</en></p>
	<p><ru>Загрузить файл лицензии</ru><en>Upload file with license</en></p>
	<p><ru>Порядок</ru><en>Order</en></p>
	<p><ru>Скрипт</ru><en>Script</en></p>
	<p><ru>Где используется</ru><en>Usage</en></p>
	<p><ru>Показать</ru><en>Show</en></p>
	<p><ru>Лог изменений</ru><en>Change log</en></p>
	<p><ru>Создан (статус)</ru><en>Created (status)</en></p>
	<p><ru>Исполнители</ru><en>Executors</en></p>
	<p><ru>Роль</ru><en>Role</en></p>
	<p><ru>Создан с</ru><en>Created from</en></p>
	<p><ru>по</ru><en>to</en></p>
	<p><ru>Закрыт с</ru><en>Closed from</en></p>
	<p><ru>с</ru><en>from</en></p>
	<p><ru>задач</ru><en>tasks</en></p>
	<p><ru>Слияние</ru><en>Merge</en></p>
	<p><ru>Страна</ru><en>Country</en></p>
	<p><ru>Город</ru><en>City</en></p>
	<p><ru>УЛИЦА</ru><en>STREET</en></p>
	<p><ru>РАЙОН</ru><en>AREA</en></p>
	<p><ru>КВАРТАЛ</ru><en>QUATER</en></p>
	<p><ru>Дом</ru><en>House</en></p>
	<p><ru>Адресный справочник</ru><en>Address catalog</en></p>
	<p><ru>Создать нового контрагента</ru><en>Create new customer</en></p>
	<p><ru>Редактор дома</ru><en>House editor</en></p>
	<p><ru>Район</ru><en>Area</en></p>
	<p><ru>Квартал</ru><en>Quarter</en></p>
	<p><ru>Номер дома с дробью</ru><en>House number with fraction</en></p>
	<p><ru>Почтовый индекс</ru><en>Postcode</en></p>
	<p><ru>Коментарий</ru><en>Comment</en></p>
	<p><ru>ПАРАМЕТРЫ</ru><en>PARAMETERS</en></p>
	<p><ru>Индекс</ru><en>Postcode</en></p>
	<p><ru>квартала</ru><en>quater</en></p>
	<p><ru>района</ru><en>area</en></p>
	<p><ru>улицы</ru><en>street</en></p>
	<p><ru>Открыт</ru><en>Open</en></p>
	<p><ru>Сумма</ru><en>Total</en></p>
	<p><ru>Дата</ru><en>Date</en></p>
	<p><ru>Подгрупп</ru><en>Subgroups</en></p>
	<p><ru>Скрытая</ru><en>Hidden</en></p>
	<p><ru>Группы пользователей</ru><en>Groups of users</en></p>
	<p><ru>Роли</ru><en>Roles</en></p>
	<p><ru>Права</ru><en>Permissions</en></p>
	<p><ru>Фильтр по наименованию</ru><en>Filter by title</en></p>
	<p><ru>значение не установлено</ru><en>value is undefined</en></p>
	<p><ru>Включить</ru><en>Turn on</en></p>
	<p><ru>Выключить</ru><en>Turn off</en></p>
	<p><ru>Текущий лог</ru><en>Current log</en></p>
	<p><ru>Тип сообщения</ru><en>Message type</en></p>
	<p><ru>все</ru><en>all</en></p>
	<p><ru>Обратная</ru><en>Descending</en></p>
	<p><ru>Прямая</ru><en>Ascending</en></p>
	<p><ru>Тема</ru><en>Subject</en></p>
	<p><ru>От</ru><en>From</en></p>
	<p><ru>Кому</ru><en>To</en></p>
	<p><ru>Обработаны</ru><en>Processed</en></p>
	<p><ru>Сортировка</ru><en>Sorting</en></p>
	<p><ru>Создать процесс</ru><en>Create process</en></p>
	<p><ru>Фильтр - вернуться в полный</ru><en>Filter - return to full</en></p>
	<p><ru>Фильтр - удалить</ru><en>Filter - delete</en></p>
	<p><ru>Фильтр - извлечь в полный</ru><en>Filter - extract to full</en></p>
	<p><ru>Фильтр - счетчик на панель</ru><en>Filter - counter on panel</en></p>
	<p><ru>Фильтр - счетчик убрать с панели</ru><en>Filter - remove counter from panel</en></p>
	<p><ru>Фильтр - сохранённые</ru><en>Filter - saved</en></p>
	<p><ru>Фильтр - сохранить</ru><en>Filter - save</en></p>
	<p><ru>Фильтр - сброс</ru><en>Filter - reset</en></p>
	<p><ru>Фильтр не выбран</ru><en>Filter - not selected</en></p>
	<p><ru>Удалить сохранённый фильтр</ru><en>Delete saved filter</en></p>
	<p><ru>Выгрузка в Excel</ru><en>Export to Excel</en></p>
	<p><ru>Класс выполнен, проверьте логи</ru><en>Class was exectuted, check logs</en></p>
	<p><ru>Класс запущен в отдельном потоке,\nвывод в логах.</ru><en>Class was started in separated thread,\nsee output in logs.</en></p>
	<p><ru>Выполнить</ru><en>Run</en></p>
	<p><ru>Ожидание окончания выполнения</ru><en>Wait of execution is done</en></p>
	<p><ru>синхронно</ru><en>synch</en></p>
	<p><ru>Скомпилировать всё</ru><en>Recompile all</en></p>
	<p><ru>Имя класса, реализующего java.lang.Runnable</ru><en>Class name, implementing java.lang.Runnable</en></p>
	<p><ru>Custom</ru><en>Custom</en></p>
	<p><ru>Результат компиляции</ru><en>Compilation result</en></p>
	<p><ru>Класс не найден: %s</ru><en>Class not found: %s</en></p>
	<p><ru>Класс не реализует java.lang.Runnable: %s</ru><en>Class does not implement java.lang.Runnable: %s</en></p>
	<p><ru>Вы уверены, что хотите удалить?</ru><en>Are you sure you want to delete it?</en></p>
	<p><ru>Такое имя уже существует в данной ветке.</ru><en>Such name already exists here.</en></p>
	<p><ru>Фильтр по наименованию, конфигурации</ru><en>Filter by title, configuration</en></p>
	<p><ru>Не найдены файлы обновлений.</ru><en>Update files not found.</en></p>
	<p><ru>Использующие очереди</ru><en>Using queues</en></p>
	<p><ru>Копировать свойства другого типа</ru><en>Copy properties from another type</en></p>
	<p><ru>Редактор типа</ru><en>Type editor</en></p>
	<p><ru>Восстановить</ru><en>Reestablish</en></p>
	<p><ru>Свойства типа</ru><en>Type properties</en></p>
	<p><ru>К списку типов</ru><en>To the list of types</en></p>
	<p><ru>Название фильтра</ru><en>Filter title</en></p>
	<p><ru>Введите название!</ru><en>Input title!</en></p>
	<p><ru>Скрыть</ru><en>Hide</en></p>
	<p><ru>Отобразить</ru><en>Show</en></p>
	<p><ru>Перезапустить</ru><en>Restart</en></p>
	<p><ru>Ошибка в параметрах запроса</ru><en>Error in request parameters</en></p>
	<p><ru>Сохранить без выхода из редактора</ru><en>Save without leaving editor</en></p>
	<!-- <p><ru>Отчёт не найден.</ru><en>Report not found.</en></p> -->
	<p><ru>Созданные</ru><en>Created</en></p>
	<p><ru>Вам не разрешён доступ к очереди процессов с ID=%s</ru><en>You are not allowed to access the process queue with ID=%s</en></p>
	<p><ru>Освободить</ru><en>Release</en></p>
	<p><ru>Принят</ru><en>Accepted</en></p>
	<p><ru>Сессии (вход / последняя активность)</ru><en>Sessions (login / last activity)</en></p>
	<p><ru>Обновление</ru><en>Update</en></p>
	<p><ru>Принудительно</ru><en>Force</en></p>
	<p><ru>Обновить</ru><en>Update</en></p>
	<p><ru>Обновление на изменение</ru><en>Update on change</en></p>
	<p><ru>ID процесса</ru><en>Process ID</en></p>
	<p><ru>Логи обновлений</ru><en>Update logs</en></p>
	<p><ru>Файл</ru><en>File</en></p>
	<p><ru>Размер</ru><en>Size</en></p>
	<p><ru>Выберите улицу</ru><en>Choose a street</en></p>
	<p><ru>Ссылается</ru><en>Linked</en></p>
	<p><ru>Зависит</ru><en>Depends</en></p>
	<p><ru>Породил</ru><en>Made</en></p>
	<p><ru>С</ru><en>L</en></p>
	<p><ru>З</ru><en>D</en></p>
	<p><ru>П</ru><en>M</en></p>
	<p><ru>Для привязки доступны процессы, выбранные в буфер</ru><en>The processes selected in the buffer are available for binding</en></p>
	<p><ru>Шаблон</ru><en>Template</en></p>
	<p><ru>С даты</ru><en>From date</en></p>
	<p><ru>По дату</ru><en>To date</en></p>
	<p><ru>Фильтр по IP адресу</ru><en>Filter by IP address</en></p>
	<p><ru>Фильтр по Параметрам</ru><en>Filter by Parameters</en></p>
	<p><ru>Фильтр по действию</ru><en>Filter by action</en></p>
	<p><ru>Сортировать</ru><en>Sort</en></p>
	<p><ru>Пользователю</ru><en>User</en></p>
	<p><ru>Действию</ru><en>Action</en></p>
	<p><ru>IP адресу</ru><en>IP address</en></p>
	<p><ru>Применить</ru><en>Apply</en></p>
	<p><ru>Сохранить</ru><en>Save</en></p>
	<p><ru>Позиция</ru><en>Position</en></p>
	<p><ru>Позиция статуса в различных перечнях</ru><en>Position of status in various lists</en></p>
	<p><ru>Наследовать свойства от предка</ru><en>Inherit properties from parent</en></p>
	<p><ru>Значения</ru><en>Values</en></p>
	<p><ru>Запрещено повторное добавление файла с одинаковым именем.</ru><en>Adding file with same name two times is denied.</en></p>
	<p><ru>Заменить права набора на права из другого набора</ru><en>Replace set permissions with permissions from another set</en></p>
	<p><ru>Фильтр по наименованию, комментарию, конфигурации, параметрам действий</ru><en>Filter by name, comment, configuration, action parameters</en></p>
	<p><ru>Сбросить выделение</ru><en>Reset selection</en></p>
	<p><ru>Лог изменений параметров</ru><en>Parameter change log</en></p>
	<p><ru>Обработка</ru><en>Processing</en></p>
	<p><ru>Создать новый процесс</ru><en>Create a new process</en></p>
	<p><ru>Привязать</ru><en>Bind</en></p>
	<p><ru>Укажите код для привязки процесса. Код "0" - для отвязки сообщения от процесса.</ru><en>Provide the code to bind the process. Code "0" - to decouple the message from the process.</en></p>
	<p><ru>Вложения (можно загрузить только после привязки процесса)</ru><en>Attachments (can only be downloaded after linking the process)</en></p>
	<p><ru>С номера</ru><en>From number</en></p>
	<p><ru>На номер</ru><en>To the number</en></p>
	<p><ru>Время начала</ru><en>Start time</en></p>
	<p><ru>Привязать процесс</ru><en>Link a process</en></p>
	<p><ru>Возможные процессы</ru><en>Possible processes</en></p>
	<p><ru>Выберите тип</ru><en>Select type</en></p>
	<p><ru>Краткое описание процесса</ru><en>Brief description of the process</en></p>
	<p><ru>Сообщение</ru><en>Message</en></p>
	<p><ru>Уведомление</ru><en>Notification</en></p>
	<p><ru>Контакт</ru><en>Contact</en></p>
	<p><ru>Только открытые</ru><en>Open only</en></p>
	<p><ru>Не сохранять</ru><en>Do not save</en></p>
	<p><ru>Cохранить EMail</ru><en>Save EMail</en></p>
	<p><ru>Cохранить EMail домен</ru><en>Save EMail domain</en></p>
	<p><ru>Время закрытия</ru><en>Closing time</en></p>
	<p><ru>Дата генерации</ru><en>Generation date</en></p>
	<p><ru>Тест title</ru><en>Test title</en></p>
	<p><ru>Тест state</ru><en>Test state</en></p>
	<p><ru>Ядро</ru><en>Kernel</en></p>
	<p><ru>Группы и пользователи</ru><en>Groups and users</en></p>
	<p><ru>Больше</ru><en>More</en></p>
	<p><ru>График</ru><en>Chart</en></p>
	<!--
	<p><ru></ru><en></en></p>
	-->
</data>